client/__init__.py
client/add_contact.py
client/database.py
client/del_contact.py
client/main_window.py
client/main_window_conv.py
client/start_dialog.py
client/transport.py
common/__init__.py
common/decoration.py
common/descriptors.py
common/errors.py
common/metaclasses.py
common/utils.py
common/variables.py
client_part-0.0.1.dist-info/METADATA
client_part-0.0.1.dist-info/WHEEL
client_part-0.0.1.dist-info/top_level.txt
client_part-0.0.1.dist-info/RECORD
